{
  "namespaces": [
    "public"
  ],
  "name": "public",
  "tables": [
    {
      "columns": {
        "id": {
          "name": "id",
          "type": "uuid",
          "unsigned": false,
          "autoincrement": false,
          "primary": false,
          "nullable": false,
          "default": "gen_random_uuid()",
          "mappedType": "uuid"
        },
        "created_at": {
          "name": "created_at",
          "type": "timestamptz",
          "unsigned": false,
          "autoincrement": false,
          "primary": false,
          "nullable": false,
          "length": 6,
          "mappedType": "datetime"
        },
        "updated_at": {
          "name": "updated_at",
          "type": "timestamptz",
          "unsigned": false,
          "autoincrement": false,
          "primary": false,
          "nullable": false,
          "length": 6,
          "mappedType": "datetime"
        },
        "code": {
          "name": "code",
          "type": "varchar(255)",
          "unsigned": false,
          "autoincrement": false,
          "primary": false,
          "nullable": false,
          "length": 255,
          "mappedType": "string"
        },
        "description": {
          "name": "description",
          "type": "varchar(255)",
          "unsigned": false,
          "autoincrement": false,
          "primary": false,
          "nullable": false,
          "length": 255,
          "mappedType": "string"
        }
      },
      "name": "gender",
      "schema": "public",
      "indexes": [
        {
          "columnNames": [
            "code"
          ],
          "composite": false,
          "keyName": "gender_code_unique",
          "constraint": true,
          "primary": false,
          "unique": true
        },
        {
          "keyName": "gender_pkey",
          "columnNames": [
            "id"
          ],
          "composite": false,
          "constraint": true,
          "primary": true,
          "unique": true
        }
      ],
      "checks": [],
      "foreignKeys": {},
      "nativeEnums": {}
    },
    {
      "columns": {
        "id": {
          "name": "id",
          "type": "uuid",
          "unsigned": false,
          "autoincrement": false,
          "primary": false,
          "nullable": false,
          "default": "gen_random_uuid()",
          "mappedType": "uuid"
        },
        "created_at": {
          "name": "created_at",
          "type": "timestamptz",
          "unsigned": false,
          "autoincrement": false,
          "primary": false,
          "nullable": false,
          "length": 6,
          "mappedType": "datetime"
        },
        "updated_at": {
          "name": "updated_at",
          "type": "timestamptz",
          "unsigned": false,
          "autoincrement": false,
          "primary": false,
          "nullable": false,
          "length": 6,
          "mappedType": "datetime"
        },
        "code": {
          "name": "code",
          "type": "varchar(255)",
          "unsigned": false,
          "autoincrement": false,
          "primary": false,
          "nullable": false,
          "length": 255,
          "mappedType": "string"
        },
        "description": {
          "name": "description",
          "type": "varchar(255)",
          "unsigned": false,
          "autoincrement": false,
          "primary": false,
          "nullable": false,
          "length": 255,
          "mappedType": "string"
        }
      },
      "name": "muscle_group",
      "schema": "public",
      "indexes": [
        {
          "columnNames": [
            "code"
          ],
          "composite": false,
          "keyName": "muscle_group_code_unique",
          "constraint": true,
          "primary": false,
          "unique": true
        },
        {
          "keyName": "muscle_group_pkey",
          "columnNames": [
            "id"
          ],
          "composite": false,
          "constraint": true,
          "primary": true,
          "unique": true
        }
      ],
      "checks": [],
      "foreignKeys": {},
      "nativeEnums": {}
    },
    {
      "columns": {
        "id": {
          "name": "id",
          "type": "uuid",
          "unsigned": false,
          "autoincrement": false,
          "primary": false,
          "nullable": false,
          "default": "gen_random_uuid()",
          "mappedType": "uuid"
        },
        "created_at": {
          "name": "created_at",
          "type": "timestamptz",
          "unsigned": false,
          "autoincrement": false,
          "primary": false,
          "nullable": false,
          "length": 6,
          "mappedType": "datetime"
        },
        "updated_at": {
          "name": "updated_at",
          "type": "timestamptz",
          "unsigned": false,
          "autoincrement": false,
          "primary": false,
          "nullable": false,
          "length": 6,
          "mappedType": "datetime"
        },
        "name": {
          "name": "name",
          "type": "varchar(255)",
          "unsigned": false,
          "autoincrement": false,
          "primary": false,
          "nullable": false,
          "length": 255,
          "mappedType": "string"
        },
        "email": {
          "name": "email",
          "type": "varchar(255)",
          "unsigned": false,
          "autoincrement": false,
          "primary": false,
          "nullable": false,
          "length": 255,
          "mappedType": "string"
        },
        "type": {
          "name": "type",
          "type": "varchar(255)",
          "unsigned": false,
          "autoincrement": false,
          "primary": false,
          "nullable": false,
          "length": 255,
          "mappedType": "string"
        }
      },
      "name": "professionals",
      "schema": "public",
      "indexes": [
        {
          "keyName": "professionals_pkey",
          "columnNames": [
            "id"
          ],
          "composite": false,
          "constraint": true,
          "primary": true,
          "unique": true
        }
      ],
      "checks": [],
      "foreignKeys": {},
      "nativeEnums": {}
    },
    {
      "columns": {
        "id": {
          "name": "id",
          "type": "uuid",
          "unsigned": false,
          "autoincrement": false,
          "primary": false,
          "nullable": false,
          "default": "gen_random_uuid()",
          "mappedType": "uuid"
        },
        "created_at": {
          "name": "created_at",
          "type": "timestamptz",
          "unsigned": false,
          "autoincrement": false,
          "primary": false,
          "nullable": false,
          "length": 6,
          "mappedType": "datetime"
        },
        "updated_at": {
          "name": "updated_at",
          "type": "timestamptz",
          "unsigned": false,
          "autoincrement": false,
          "primary": false,
          "nullable": false,
          "length": 6,
          "mappedType": "datetime"
        },
        "code": {
          "name": "code",
          "type": "varchar(255)",
          "unsigned": false,
          "autoincrement": false,
          "primary": false,
          "nullable": false,
          "length": 255,
          "mappedType": "string"
        },
        "description": {
          "name": "description",
          "type": "varchar(255)",
          "unsigned": false,
          "autoincrement": false,
          "primary": false,
          "nullable": false,
          "length": 255,
          "mappedType": "string"
        }
      },
      "name": "restriction",
      "schema": "public",
      "indexes": [
        {
          "columnNames": [
            "code"
          ],
          "composite": false,
          "keyName": "restriction_code_unique",
          "constraint": true,
          "primary": false,
          "unique": true
        },
        {
          "keyName": "restriction_pkey",
          "columnNames": [
            "id"
          ],
          "composite": false,
          "constraint": true,
          "primary": true,
          "unique": true
        }
      ],
      "checks": [],
      "foreignKeys": {},
      "nativeEnums": {}
    },
    {
      "columns": {
        "id": {
          "name": "id",
          "type": "uuid",
          "unsigned": false,
          "autoincrement": false,
          "primary": false,
          "nullable": false,
          "default": "gen_random_uuid()",
          "mappedType": "uuid"
        },
        "created_at": {
          "name": "created_at",
          "type": "timestamptz",
          "unsigned": false,
          "autoincrement": false,
          "primary": false,
          "nullable": false,
          "length": 6,
          "mappedType": "datetime"
        },
        "updated_at": {
          "name": "updated_at",
          "type": "timestamptz",
          "unsigned": false,
          "autoincrement": false,
          "primary": false,
          "nullable": false,
          "length": 6,
          "mappedType": "datetime"
        },
        "code": {
          "name": "code",
          "type": "varchar(255)",
          "unsigned": false,
          "autoincrement": false,
          "primary": false,
          "nullable": false,
          "length": 255,
          "mappedType": "string"
        },
        "description": {
          "name": "description",
          "type": "varchar(255)",
          "unsigned": false,
          "autoincrement": false,
          "primary": false,
          "nullable": false,
          "length": 255,
          "mappedType": "string"
        }
      },
      "name": "training_type",
      "schema": "public",
      "indexes": [
        {
          "columnNames": [
            "code"
          ],
          "composite": false,
          "keyName": "training_type_code_unique",
          "constraint": true,
          "primary": false,
          "unique": true
        },
        {
          "keyName": "training_type_pkey",
          "columnNames": [
            "id"
          ],
          "composite": false,
          "constraint": true,
          "primary": true,
          "unique": true
        }
      ],
      "checks": [],
      "foreignKeys": {},
      "nativeEnums": {}
    },
    {
      "columns": {
        "id": {
          "name": "id",
          "type": "uuid",
          "unsigned": false,
          "autoincrement": false,
          "primary": false,
          "nullable": false,
          "default": "gen_random_uuid()",
          "mappedType": "uuid"
        },
        "created_at": {
          "name": "created_at",
          "type": "timestamptz",
          "unsigned": false,
          "autoincrement": false,
          "primary": false,
          "nullable": false,
          "length": 6,
          "mappedType": "datetime"
        },
        "updated_at": {
          "name": "updated_at",
          "type": "timestamptz",
          "unsigned": false,
          "autoincrement": false,
          "primary": false,
          "nullable": false,
          "length": 6,
          "mappedType": "datetime"
        },
        "full_name": {
          "name": "full_name",
          "type": "varchar(255)",
          "unsigned": false,
          "autoincrement": false,
          "primary": false,
          "nullable": false,
          "length": 255,
          "mappedType": "string"
        },
        "email": {
          "name": "email",
          "type": "varchar(255)",
          "unsigned": false,
          "autoincrement": false,
          "primary": false,
          "nullable": false,
          "length": 255,
          "mappedType": "string"
        },
        "nickname": {
          "name": "nickname",
          "type": "varchar(255)",
          "unsigned": false,
          "autoincrement": false,
          "primary": false,
          "nullable": true,
          "length": 255,
          "mappedType": "string"
        },
        "password": {
          "name": "password",
          "type": "varchar(255)",
          "unsigned": false,
          "autoincrement": false,
          "primary": false,
          "nullable": false,
          "length": 255,
          "mappedType": "string"
        },
        "age": {
          "name": "age",
          "type": "varchar(255)",
          "unsigned": false,
          "autoincrement": false,
          "primary": false,
          "nullable": false,
          "length": 255,
          "mappedType": "string"
        },
        "height": {
          "name": "height",
          "type": "varchar(255)",
          "unsigned": false,
          "autoincrement": false,
          "primary": false,
          "nullable": false,
          "length": 255,
          "mappedType": "string"
        },
        "weight": {
          "name": "weight",
          "type": "varchar(255)",
          "unsigned": false,
          "autoincrement": false,
          "primary": false,
          "nullable": false,
          "length": 255,
          "mappedType": "string"
        },
        "gender_id": {
          "name": "gender_id",
          "type": "uuid",
          "unsigned": false,
          "autoincrement": false,
          "primary": false,
          "nullable": false,
          "mappedType": "uuid"
        },
        "restriction_id": {
          "name": "restriction_id",
          "type": "uuid",
          "unsigned": false,
          "autoincrement": false,
          "primary": false,
          "nullable": true,
          "mappedType": "uuid"
        },
        "role": {
          "name": "role",
          "type": "text",
          "unsigned": false,
          "autoincrement": false,
          "primary": false,
          "nullable": false,
          "enumItems": [
            "user",
            "personal_trainer",
            "nutritionist",
            "gym"
          ],
          "mappedType": "enum"
        }
      },
      "name": "user",
      "schema": "public",
      "indexes": [
        {
          "columnNames": [
            "gender_id"
          ],
          "composite": false,
          "keyName": "user_gender_id_index",
          "constraint": false,
          "primary": false,
          "unique": false
        },
        {
          "columnNames": [
            "restriction_id"
          ],
          "composite": false,
          "keyName": "user_restriction_id_index",
          "constraint": false,
          "primary": false,
          "unique": false
        },
        {
          "keyName": "user_pkey",
          "columnNames": [
            "id"
          ],
          "composite": false,
          "constraint": true,
          "primary": true,
          "unique": true
        }
      ],
      "checks": [],
      "foreignKeys": {
        "user_gender_id_foreign": {
          "constraintName": "user_gender_id_foreign",
          "columnNames": [
            "gender_id"
          ],
          "localTableName": "public.user",
          "referencedColumnNames": [
            "id"
          ],
          "referencedTableName": "public.gender",
          "updateRule": "cascade"
        },
        "user_restriction_id_foreign": {
          "constraintName": "user_restriction_id_foreign",
          "columnNames": [
            "restriction_id"
          ],
          "localTableName": "public.user",
          "referencedColumnNames": [
            "id"
          ],
          "referencedTableName": "public.restriction",
          "deleteRule": "set null",
          "updateRule": "cascade"
        }
      },
      "nativeEnums": {}
    },
    {
      "columns": {
        "professionals_id": {
          "name": "professionals_id",
          "type": "uuid",
          "unsigned": false,
          "autoincrement": false,
          "primary": false,
          "nullable": false,
          "mappedType": "uuid"
        },
        "user_id": {
          "name": "user_id",
          "type": "uuid",
          "unsigned": false,
          "autoincrement": false,
          "primary": false,
          "nullable": false,
          "mappedType": "uuid"
        }
      },
      "name": "professionals_users",
      "schema": "public",
      "indexes": [
        {
          "keyName": "professionals_users_pkey",
          "columnNames": [
            "professionals_id",
            "user_id"
          ],
          "composite": true,
          "constraint": true,
          "primary": true,
          "unique": true
        }
      ],
      "checks": [],
      "foreignKeys": {
        "professionals_users_professionals_id_foreign": {
          "constraintName": "professionals_users_professionals_id_foreign",
          "columnNames": [
            "professionals_id"
          ],
          "localTableName": "public.professionals_users",
          "referencedColumnNames": [
            "id"
          ],
          "referencedTableName": "public.professionals",
          "deleteRule": "cascade",
          "updateRule": "cascade"
        },
        "professionals_users_user_id_foreign": {
          "constraintName": "professionals_users_user_id_foreign",
          "columnNames": [
            "user_id"
          ],
          "localTableName": "public.professionals_users",
          "referencedColumnNames": [
            "id"
          ],
          "referencedTableName": "public.user",
          "deleteRule": "cascade",
          "updateRule": "cascade"
        }
      },
      "nativeEnums": {}
    },
    {
      "columns": {
        "id": {
          "name": "id",
          "type": "uuid",
          "unsigned": false,
          "autoincrement": false,
          "primary": false,
          "nullable": false,
          "default": "gen_random_uuid()",
          "mappedType": "uuid"
        },
        "created_at": {
          "name": "created_at",
          "type": "timestamptz",
          "unsigned": false,
          "autoincrement": false,
          "primary": false,
          "nullable": false,
          "length": 6,
          "mappedType": "datetime"
        },
        "updated_at": {
          "name": "updated_at",
          "type": "timestamptz",
          "unsigned": false,
          "autoincrement": false,
          "primary": false,
          "nullable": false,
          "length": 6,
          "mappedType": "datetime"
        },
        "code": {
          "name": "code",
          "type": "varchar(255)",
          "unsigned": false,
          "autoincrement": false,
          "primary": false,
          "nullable": false,
          "length": 255,
          "mappedType": "string"
        },
        "description": {
          "name": "description",
          "type": "varchar(255)",
          "unsigned": false,
          "autoincrement": false,
          "primary": false,
          "nullable": false,
          "length": 255,
          "mappedType": "string"
        },
        "active": {
          "name": "active",
          "type": "boolean",
          "unsigned": false,
          "autoincrement": false,
          "primary": false,
          "nullable": false,
          "mappedType": "boolean"
        },
        "user_id": {
          "name": "user_id",
          "type": "uuid",
          "unsigned": false,
          "autoincrement": false,
          "primary": false,
          "nullable": true,
          "mappedType": "uuid"
        }
      },
      "name": "goals",
      "schema": "public",
      "indexes": [
        {
          "columnNames": [
            "code"
          ],
          "composite": false,
          "keyName": "goals_code_unique",
          "constraint": true,
          "primary": false,
          "unique": true
        },
        {
          "columnNames": [
            "user_id"
          ],
          "composite": false,
          "keyName": "goals_user_id_index",
          "constraint": false,
          "primary": false,
          "unique": false
        },
        {
          "keyName": "goals_pkey",
          "columnNames": [
            "id"
          ],
          "composite": false,
          "constraint": true,
          "primary": true,
          "unique": true
        }
      ],
      "checks": [],
      "foreignKeys": {
        "goals_user_id_foreign": {
          "constraintName": "goals_user_id_foreign",
          "columnNames": [
            "user_id"
          ],
          "localTableName": "public.goals",
          "referencedColumnNames": [
            "id"
          ],
          "referencedTableName": "public.user",
          "deleteRule": "set null",
          "updateRule": "cascade"
        }
      },
      "nativeEnums": {}
    },
    {
      "columns": {
        "id": {
          "name": "id",
          "type": "uuid",
          "unsigned": false,
          "autoincrement": false,
          "primary": false,
          "nullable": false,
          "default": "gen_random_uuid()",
          "mappedType": "uuid"
        },
        "created_at": {
          "name": "created_at",
          "type": "timestamptz",
          "unsigned": false,
          "autoincrement": false,
          "primary": false,
          "nullable": false,
          "length": 6,
          "mappedType": "datetime"
        },
        "updated_at": {
          "name": "updated_at",
          "type": "timestamptz",
          "unsigned": false,
          "autoincrement": false,
          "primary": false,
          "nullable": false,
          "length": 6,
          "mappedType": "datetime"
        },
        "active": {
          "name": "active",
          "type": "boolean",
          "unsigned": false,
          "autoincrement": false,
          "primary": false,
          "nullable": false,
          "mappedType": "boolean"
        },
        "training_type_id": {
          "name": "training_type_id",
          "type": "uuid",
          "unsigned": false,
          "autoincrement": false,
          "primary": false,
          "nullable": false,
          "mappedType": "uuid"
        },
        "goals_id": {
          "name": "goals_id",
          "type": "uuid",
          "unsigned": false,
          "autoincrement": false,
          "primary": false,
          "nullable": true,
          "mappedType": "uuid"
        },
        "user_id": {
          "name": "user_id",
          "type": "uuid",
          "unsigned": false,
          "autoincrement": false,
          "primary": false,
          "nullable": false,
          "mappedType": "uuid"
        }
      },
      "name": "training",
      "schema": "public",
      "indexes": [
        {
          "columnNames": [
            "training_type_id"
          ],
          "composite": false,
          "keyName": "training_training_type_id_index",
          "constraint": false,
          "primary": false,
          "unique": false
        },
        {
          "columnNames": [
            "goals_id"
          ],
          "composite": false,
          "keyName": "training_goals_id_index",
          "constraint": false,
          "primary": false,
          "unique": false
        },
        {
          "columnNames": [
            "user_id"
          ],
          "composite": false,
          "keyName": "training_user_id_index",
          "constraint": false,
          "primary": false,
          "unique": false
        },
        {
          "keyName": "training_pkey",
          "columnNames": [
            "id"
          ],
          "composite": false,
          "constraint": true,
          "primary": true,
          "unique": true
        }
      ],
      "checks": [],
      "foreignKeys": {
        "training_training_type_id_foreign": {
          "constraintName": "training_training_type_id_foreign",
          "columnNames": [
            "training_type_id"
          ],
          "localTableName": "public.training",
          "referencedColumnNames": [
            "id"
          ],
          "referencedTableName": "public.training_type",
          "updateRule": "cascade"
        },
        "training_goals_id_foreign": {
          "constraintName": "training_goals_id_foreign",
          "columnNames": [
            "goals_id"
          ],
          "localTableName": "public.training",
          "referencedColumnNames": [
            "id"
          ],
          "referencedTableName": "public.goals",
          "deleteRule": "set null",
          "updateRule": "cascade"
        },
        "training_user_id_foreign": {
          "constraintName": "training_user_id_foreign",
          "columnNames": [
            "user_id"
          ],
          "localTableName": "public.training",
          "referencedColumnNames": [
            "id"
          ],
          "referencedTableName": "public.user",
          "updateRule": "cascade"
        }
      },
      "nativeEnums": {}
    },
    {
      "columns": {
        "id": {
          "name": "id",
          "type": "uuid",
          "unsigned": false,
          "autoincrement": false,
          "primary": false,
          "nullable": false,
          "default": "gen_random_uuid()",
          "mappedType": "uuid"
        },
        "created_at": {
          "name": "created_at",
          "type": "timestamptz",
          "unsigned": false,
          "autoincrement": false,
          "primary": false,
          "nullable": false,
          "length": 6,
          "mappedType": "datetime"
        },
        "updated_at": {
          "name": "updated_at",
          "type": "timestamptz",
          "unsigned": false,
          "autoincrement": false,
          "primary": false,
          "nullable": false,
          "length": 6,
          "mappedType": "datetime"
        },
        "code": {
          "name": "code",
          "type": "varchar(255)",
          "unsigned": false,
          "autoincrement": false,
          "primary": false,
          "nullable": false,
          "length": 255,
          "mappedType": "string"
        },
        "description": {
          "name": "description",
          "type": "varchar(255)",
          "unsigned": false,
          "autoincrement": false,
          "primary": false,
          "nullable": false,
          "length": 255,
          "mappedType": "string"
        },
        "muscle_group_id": {
          "name": "muscle_group_id",
          "type": "uuid",
          "unsigned": false,
          "autoincrement": false,
          "primary": false,
          "nullable": true,
          "mappedType": "uuid"
        },
        "user_id": {
          "name": "user_id",
          "type": "uuid",
          "unsigned": false,
          "autoincrement": false,
          "primary": false,
          "nullable": true,
          "mappedType": "uuid"
        }
      },
      "name": "exercise",
      "schema": "public",
      "indexes": [
        {
          "columnNames": [
            "code"
          ],
          "composite": false,
          "keyName": "exercise_code_unique",
          "constraint": true,
          "primary": false,
          "unique": true
        },
        {
          "columnNames": [
            "muscle_group_id"
          ],
          "composite": false,
          "keyName": "exercise_muscle_group_id_index",
          "constraint": false,
          "primary": false,
          "unique": false
        },
        {
          "columnNames": [
            "user_id"
          ],
          "composite": false,
          "keyName": "exercise_user_id_index",
          "constraint": false,
          "primary": false,
          "unique": false
        },
        {
          "keyName": "exercise_pkey",
          "columnNames": [
            "id"
          ],
          "composite": false,
          "constraint": true,
          "primary": true,
          "unique": true
        }
      ],
      "checks": [],
      "foreignKeys": {
        "exercise_muscle_group_id_foreign": {
          "constraintName": "exercise_muscle_group_id_foreign",
          "columnNames": [
            "muscle_group_id"
          ],
          "localTableName": "public.exercise",
          "referencedColumnNames": [
            "id"
          ],
          "referencedTableName": "public.muscle_group",
          "deleteRule": "set null",
          "updateRule": "cascade"
        },
        "exercise_user_id_foreign": {
          "constraintName": "exercise_user_id_foreign",
          "columnNames": [
            "user_id"
          ],
          "localTableName": "public.exercise",
          "referencedColumnNames": [
            "id"
          ],
          "referencedTableName": "public.user",
          "deleteRule": "set null",
          "updateRule": "cascade"
        }
      },
      "nativeEnums": {}
    },
    {
      "columns": {
        "id": {
          "name": "id",
          "type": "uuid",
          "unsigned": false,
          "autoincrement": false,
          "primary": false,
          "nullable": false,
          "default": "gen_random_uuid()",
          "mappedType": "uuid"
        },
        "created_at": {
          "name": "created_at",
          "type": "timestamptz",
          "unsigned": false,
          "autoincrement": false,
          "primary": false,
          "nullable": false,
          "length": 6,
          "mappedType": "datetime"
        },
        "updated_at": {
          "name": "updated_at",
          "type": "timestamptz",
          "unsigned": false,
          "autoincrement": false,
          "primary": false,
          "nullable": false,
          "length": 6,
          "mappedType": "datetime"
        },
        "sets": {
          "name": "sets",
          "type": "int",
          "unsigned": false,
          "autoincrement": false,
          "primary": false,
          "nullable": true,
          "mappedType": "integer"
        },
        "reps": {
          "name": "reps",
          "type": "varchar(255)",
          "unsigned": false,
          "autoincrement": false,
          "primary": false,
          "nullable": true,
          "length": 255,
          "mappedType": "string"
        },
        "rest_time": {
          "name": "rest_time",
          "type": "varchar(255)",
          "unsigned": false,
          "autoincrement": false,
          "primary": false,
          "nullable": true,
          "length": 255,
          "mappedType": "string"
        },
        "training_id": {
          "name": "training_id",
          "type": "uuid",
          "unsigned": false,
          "autoincrement": false,
          "primary": false,
          "nullable": true,
          "mappedType": "uuid"
        },
        "exercise_id": {
          "name": "exercise_id",
          "type": "uuid",
          "unsigned": false,
          "autoincrement": false,
          "primary": false,
          "nullable": true,
          "mappedType": "uuid"
        }
      },
      "name": "training_exercise",
      "schema": "public",
      "indexes": [
        {
          "columnNames": [
            "training_id"
          ],
          "composite": false,
          "keyName": "training_exercise_training_id_index",
          "constraint": false,
          "primary": false,
          "unique": false
        },
        {
          "columnNames": [
            "exercise_id"
          ],
          "composite": false,
          "keyName": "training_exercise_exercise_id_index",
          "constraint": false,
          "primary": false,
          "unique": false
        },
        {
          "keyName": "training_exercise_pkey",
          "columnNames": [
            "id"
          ],
          "composite": false,
          "constraint": true,
          "primary": true,
          "unique": true
        }
      ],
      "checks": [],
      "foreignKeys": {
        "training_exercise_training_id_foreign": {
          "constraintName": "training_exercise_training_id_foreign",
          "columnNames": [
            "training_id"
          ],
          "localTableName": "public.training_exercise",
          "referencedColumnNames": [
            "id"
          ],
          "referencedTableName": "public.training",
          "deleteRule": "set null",
          "updateRule": "cascade"
        },
        "training_exercise_exercise_id_foreign": {
          "constraintName": "training_exercise_exercise_id_foreign",
          "columnNames": [
            "exercise_id"
          ],
          "localTableName": "public.training_exercise",
          "referencedColumnNames": [
            "id"
          ],
          "referencedTableName": "public.exercise",
          "deleteRule": "set null",
          "updateRule": "cascade"
        }
      },
      "nativeEnums": {}
    },
    {
      "columns": {
        "id": {
          "name": "id",
          "type": "uuid",
          "unsigned": false,
          "autoincrement": false,
          "primary": false,
          "nullable": false,
          "default": "gen_random_uuid()",
          "mappedType": "uuid"
        },
        "created_at": {
          "name": "created_at",
          "type": "timestamptz",
          "unsigned": false,
          "autoincrement": false,
          "primary": false,
          "nullable": false,
          "length": 6,
          "mappedType": "datetime"
        },
        "updated_at": {
          "name": "updated_at",
          "type": "timestamptz",
          "unsigned": false,
          "autoincrement": false,
          "primary": false,
          "nullable": false,
          "length": 6,
          "mappedType": "datetime"
        },
        "user_id": {
          "name": "user_id",
          "type": "uuid",
          "unsigned": false,
          "autoincrement": false,
          "primary": false,
          "nullable": false,
          "mappedType": "uuid"
        },
        "pre_existing_health_conditions": {
          "name": "pre_existing_health_conditions",
          "type": "text[]",
          "unsigned": false,
          "autoincrement": false,
          "primary": false,
          "nullable": true,
          "mappedType": "array"
        },
        "medication_use": {
          "name": "medication_use",
          "type": "text[]",
          "unsigned": false,
          "autoincrement": false,
          "primary": false,
          "nullable": true,
          "mappedType": "array"
        },
        "time_training_weightlifting": {
          "name": "time_training_weightlifting",
          "type": "varchar(255)",
          "unsigned": false,
          "autoincrement": false,
          "primary": false,
          "nullable": true,
          "length": 255,
          "mappedType": "string"
        },
        "training_frequency": {
          "name": "training_frequency",
          "type": "varchar(255)",
          "unsigned": false,
          "autoincrement": false,
          "primary": false,
          "nullable": true,
          "length": 255,
          "mappedType": "string"
        },
        "time_availability_per_training": {
          "name": "time_availability_per_training",
          "type": "varchar(255)",
          "unsigned": false,
          "autoincrement": false,
          "primary": false,
          "nullable": true,
          "length": 255,
          "mappedType": "string"
        },
        "other_regular_physical_activity": {
          "name": "other_regular_physical_activity",
          "type": "text[]",
          "unsigned": false,
          "autoincrement": false,
          "primary": false,
          "nullable": true,
          "mappedType": "array"
        },
        "liked_disliked_exercises": {
          "name": "liked_disliked_exercises",
          "type": "varchar(255)",
          "unsigned": false,
          "autoincrement": false,
          "primary": false,
          "nullable": true,
          "length": 255,
          "mappedType": "string"
        },
        "muscle_focus": {
          "name": "muscle_focus",
          "type": "text[]",
          "unsigned": false,
          "autoincrement": false,
          "primary": false,
          "nullable": true,
          "mappedType": "array"
        }
      },
      "name": "additional_info",
      "schema": "public",
      "indexes": [
        {
          "columnNames": [
            "user_id"
          ],
          "composite": false,
          "keyName": "additional_info_user_id_index",
          "constraint": false,
          "primary": false,
          "unique": false
        },
        {
          "keyName": "additional_info_pkey",
          "columnNames": [
            "id"
          ],
          "composite": false,
          "constraint": true,
          "primary": true,
          "unique": true
        }
      ],
      "checks": [],
      "foreignKeys": {
        "additional_info_user_id_foreign": {
          "constraintName": "additional_info_user_id_foreign",
          "columnNames": [
            "user_id"
          ],
          "localTableName": "public.additional_info",
          "referencedColumnNames": [
            "id"
          ],
          "referencedTableName": "public.user",
          "updateRule": "cascade"
        }
      },
      "nativeEnums": {}
    }
  ],
  "nativeEnums": {}
}
